{"reviewList":["review653","review1363","review3273","review3763","review4800","review6588","review7369","review7526","review8271","review8526","review8983"],"type":"product","imageURL":"http://ecx.images-amazon.com/images/I/41-8IpyUBAL._SL300_.jpg","dateModified":"2014-05-06T15:52:19Z","productId":"product772","unitPrice":39.0,"dateAdded":"2013-08-09T15:52:19Z","description":"This product is available on <a target=\"_blank\" href=\"http://www.amazon.com/gp/product/B00717AHDK/ref=s9_hps_bw_g200_ir014?pf_rd_m=ATVPDKIKX0DER&pf_rd_s=merchandised-search-5&pf_rd_r=426FF5E61BCB47CF8179&pf_rd_t=101&pf_rd_p=1531656862&pf_rd_i=3403201\">Amazon.com</a>.","name":"Yakima Whispbar Fitting Kit","categories":["Cycling"],"color":"sky blue"}