{"reviewList":["review729","review1288","review1461","review2705","review2981","review3602","review4764","review5031","review5656","review9166"],"type":"product","imageURL":"http://ecx.images-amazon.com/images/I/41bWTkh-ZXL._SL300_.jpg","dateModified":"2014-05-06T15:52:19Z","productId":"product822","unitPrice":25.0,"dateAdded":"2013-08-09T15:52:19Z","description":"This product is available on <a target=\"_blank\" href=\"http://www.amazon.com/gp/product/B005CCWQ9Y/ref=s9_hps_bw_g200_ir010?pf_rd_m=ATVPDKIKX0DER&pf_rd_s=center-24&pf_rd_r=1RCXF6AABG7YEGQEBKX5&pf_rd_t=101&pf_rd_p=1532517142&pf_rd_i=3386071\">Amazon.com</a>.","name":"MLS Portland Timbers, Authentic Draft Scarf, OSFA","categories":["Fan Shop"],"color":"cyan"}