{"reviewList":["review197","review629","review633","review778","review3750","review4421","review4920","review7431","review8435","review8485","review9523"],"type":"product","imageURL":"http://ecx.images-amazon.com/images/I/41JIl8YCXrL._SL300_.jpg","dateModified":"2014-05-06T15:52:18Z","productId":"product308","unitPrice":22.55,"dateAdded":"2014-05-06T15:52:18Z","description":"This product is available on <a target=\"_blank\" href=\"http://www.amazon.com/gp/product/B008NNZSXU/ref=s9_hps_bw_g60_ir05?pf_rd_m=ATVPDKIKX0DER&pf_rd_s=center-12&pf_rd_r=08CXQVRKD2HFBK6BS6DZ&pf_rd_t=101&pf_rd_p=1523857122&pf_rd_i=228013\">Amazon.com</a>.","name":"Philips 422154 12.5-Watt A19 LED Light Bulb, Dimmable","categories":["Home Improvement"],"color":"mint green"}