{"reviewList":["review1552","review2071","review2448","review3552","review4029","review6359","review8731"],"type":"product","imageURL":"http://ecx.images-amazon.com/images/I/41kD1%2BuXZhL._SL300_.jpg","dateModified":"2014-05-06T15:52:18Z","productId":"product500","unitPrice":100.85,"dateAdded":"2014-03-07T15:52:18Z","description":"This product is available on <a target=\"_blank\" href=\"http://www.amazon.com/gp/product/B00176FBP0/ref=s9_hps_bw_g60_ir020?pf_rd_m=ATVPDKIKX0DER&pf_rd_s=center-11&pf_rd_r=00ZRJEQP95SZ6ZTN7MCG&pf_rd_t=101&pf_rd_p=1347953162&pf_rd_i=3754161\">Amazon.com</a>.","name":"Moen 128875ORB Handshower, Oil Rubbed Bronze","categories":["Kitchen & Bath Fixtures"],"color":"olive"}