{"reviewList":["review1357","review2499","review2899","review3299","review3408","review3494","review5873","review7886"],"type":"product","imageURL":"http://ecx.images-amazon.com/images/I/41PCsr2eIhL._SL300_.jpg","dateModified":"2014-05-06T15:52:18Z","productId":"product243","unitPrice":9.9,"dateAdded":"2014-02-05T15:52:18Z","description":"This product is available on <a target=\"_blank\" href=\"http://www.amazon.com/gp/product/B004GXBYHA/ref=s9_al_bw_g201_ir020?pf_rd_m=ATVPDKIKX0DER&pf_rd_s=merchandised-search-10&pf_rd_r=EBD6B63F1A7A4E1A91A0&pf_rd_t=101&pf_rd_p=1387563682&pf_rd_i=2617941011\">Amazon.com</a>.","name":"Darice Colored Pencil and Pad, Case Combo Set","categories":["Arts, Crafts & Sewing"],"color":"tan"}