{"reviewList":["review602","review1455","review2294","review3127","review4518","review5129","review5658","review6727","review7005","review9095"],"type":"product","imageURL":"http://ecx.images-amazon.com/images/I/41LRpHXs7mL._SL300_.jpg","dateModified":"2014-05-06T15:52:19Z","productId":"product845","unitPrice":24.99,"dateAdded":"2014-03-07T15:52:19Z","description":"This product is available on <a target=\"_blank\" href=\"http://www.amazon.com/gp/product/B001D7519Y/ref=s9_hps_bw_g200_ir05?pf_rd_m=ATVPDKIKX0DER&pf_rd_s=merchandised-search-10&pf_rd_r=AF4356F23718450681C3&pf_rd_t=101&pf_rd_p=1532316542&pf_rd_i=3410851\">Amazon.com</a>.","name":"uPro Soft Case","categories":["Golf"],"color":"purple"}